requestweb.py
requestweb-1.0.1.dist-info/METADATA
requestweb-1.0.1.dist-info/WHEEL
requestweb-1.0.1.dist-info/top_level.txt
requestweb-1.0.1.dist-info/RECORD
