Metadata-Version: 2.1
Name: requestweb
Version: 1.0.1
Summary: Fastest Way to request to send HTTP/1.1 requests extremely easily also able to enable javascript for pageload and capture html code
Author: Abhiram.B
Author-email: to@abhiram.email
License: MIT
Classifier: Programming Language :: Python :: 3
Classifier: License :: OSI Approved :: MIT License
Classifier: Operating System :: OS Independent
Requires-Python: >=3.6
Requires-Dist: PyQt5
Requires-Dist: PyQtWebEngine
Requires-Dist: beautifulsoup4
Requires-Dist: python-whois
Requires-Dist: requests
